seabreeze_server/__init__.py
seabreeze_server/client.py
seabreeze_server/errors.py
seabreeze_server/server.py
seabreeze_server-0.2.1.dist-info/LICENSE
seabreeze_server-0.2.1.dist-info/METADATA
seabreeze_server-0.2.1.dist-info/WHEEL
seabreeze_server-0.2.1.dist-info/top_level.txt
seabreeze_server-0.2.1.dist-info/RECORD
