Metadata-Version: 2.1
Name: seabreeze-server
Version: 0.2.1
Summary: A TCP server to host the `python-seabreeze.cseabreeze` backend
Home-page: https://github.com/jonathanvanschenck/python-seabreeze-server
Author: Jonathan D B Van Schenck
Author-email: vanschej@oregonstate.edu
License: UNKNOWN
Platform: UNKNOWN
Classifier: Programming Language :: Python :: 3
Classifier: License :: OSI Approved :: MIT License
Classifier: Operating System :: OS Independent
Requires-Python: >=3.6
Requires-Dist: future (>=0.18.2)
Requires-Dist: numpy (>=1.18.2)
Requires-Dist: remote-object (>=0.2.4)
Requires-Dist: seabreeze (>=1.0.1)
Requires-Dist: seatease (>=0.4.0)
